{
    "form_code": "2-A",
    "internal_code": "2-A",
    "title": "Agreement of Adoption and Consent (Agency)",
    "court": "family_court",
    "category": "adoption",
    "county_specific": false,
    "counties_supported": [
        "New York",
        "Kings",
        "Queens",
        "Bronx",
        "Richmond"
    ],
    "source_files": {
        "pdf": {
            "filename": "adop2-a.pdf",
            "path": "",
            "source_url": "https://webfiles.nycourts.gov/public/2026-01/adop2-a.pdf",
            "download_status": "pending"
        },
        "wpd": {
            "filename": "adop2-a.WPD",
            "path": "",
            "source_url": "https://webfiles.nycourts.gov/public/2026-01/adop2-a.WPD",
            "download_status": "pending"
        }
    },
    "preferred_source": "pdf",
    "editable_source": "pdf",
    "wpd_conversion": {
        "original_wpd": "",
        "converted_docx": null
    },
    "fillable_pdf_available": false,
    "docx_available": false,
    "wpd_available": true,
    "import_status": "pending",
    "official_url": "https://www.nycourts.gov/forms/agreement-adoption-and-consent-agency-0",
    "case_types": [
        "Family Forms",
        "Adoption - Family"
    ],
    "aliases": [],
    "workflow_references": [],
    "fillable_strategy": "pdf_overlay",
    "field_mapping_status": "unmapped",
    "generation_ready": false
}
