{
    "form_code": "3-46",
    "internal_code": "3-46",
    "title": "Order for HIV Related Testing",
    "court": "family_court",
    "category": "general",
    "county_specific": false,
    "counties_supported": [
        "New York",
        "Kings",
        "Queens",
        "Bronx",
        "Richmond"
    ],
    "source_files": {
        "pdf": {
            "filename": "3-46.pdf",
            "path": "",
            "source_url": "https://webfiles.nycourts.gov/public/2025-12/3-46.pdf",
            "download_status": "pending"
        },
        "doc": {
            "filename": "3-46.doc",
            "path": "",
            "source_url": "https://webfiles.nycourts.gov/public/2025-12/3-46.doc",
            "download_status": "pending"
        }
    },
    "preferred_source": "pdf",
    "editable_source": "pdf",
    "wpd_conversion": [],
    "fillable_pdf_available": false,
    "docx_available": false,
    "wpd_available": false,
    "import_status": "pending",
    "official_url": "https://www.nycourts.gov/forms/order-hiv-related-testing?topic=611&wrapped=true",
    "case_types": [
        "Family Forms",
        "Juvenile Delinquency - Family"
    ],
    "aliases": [],
    "workflow_references": [],
    "fillable_strategy": "pdf_overlay",
    "field_mapping_status": "unmapped",
    "generation_ready": false
}
